ytube_podcast-1.0.1.dist-info/METADATA
ytube_podcast-1.0.1.dist-info/WHEEL
ytube_podcast-1.0.1.dist-info/entry_points.txt
ytube_podcast-1.0.1.dist-info/licenses/LICENSE
ytube_podcast/__init__.py
ytube_podcast/main.py
ytube_podcast/rumble.py
ytube_podcast-1.0.1.dist-info/RECORD
