Metadata-Version: 2.1
Name: ytube-podcast
Version: 1.0.1
Summary: Youtube to Podcast Generator
Author-Email: Paul Bailey <paul@neutron.studio>
License: BSD-3-Clause
Requires-Python: >=3.13
Requires-Dist: piou>=0.20.0
Requires-Dist: feedparser>=6.0.11
Requires-Dist: yt-dlp>=2025.9.26
Requires-Dist: ffmpeg-python>=0.2.0
Requires-Dist: python-slugify>=8.0.4
Requires-Dist: python-liquid>=2.0.2
Requires-Dist: httpx>=0.28.1
Requires-Dist: pendulum>=3.1.0
Requires-Dist: beautifulsoup4>=4.13.4
Requires-Dist: python-dateutil>=2.9.0.post0
